Metadata-Version: 1.0
Name: sitereport
Version: 1.1.3
Summary: sitereport.cn api
Home-page: https://www.sitereport.cn
Author: simon
Author-email: simon@yesiming.com
License: UNKNOWN
Platform: UNKNOWN
